openai_agent/__init__.py
openai_agent/completions.py
openai_agent/functions.py
openai_agent/messages.py
openai_agent-0.1.0.dist-info/LICENSE
openai_agent-0.1.0.dist-info/METADATA
openai_agent-0.1.0.dist-info/WHEEL
openai_agent-0.1.0.dist-info/RECORD
