Metadata-Version: 2.1
Name: openai-agent
Version: 0.1.0
Summary: Easy-to-use OpenAI Agent with support for the latest Function call feature.
Author: -LAN-
Author-email: laipz8200@outlook.com
Requires-Python: >=3.11,<4.0
Classifier: Programming Language :: Python :: 3
Classifier: Programming Language :: Python :: 3.11
Requires-Dist: loguru (>=0.7.0,<0.8.0)
Requires-Dist: openai (>=0.27.8,<0.28.0)
Requires-Dist: pydantic (>=1.10.9,<2.0.0)
